{"ongoing_trials": {}, "hyperparameters": {"space": [{"class_name": "Choice", "config": {"name": "learning_rate", "default": 0.005, "conditions": [], "values": [0.005, 0.0025, 0.001, 0.0005, 0.0001], "ordered": true}}, {"class_name": "Choice", "config": {"name": "loss_fun", "default": "MADL2", "conditions": [], "values": ["MADL2"], "ordered": false}}, {"class_name": "Choice", "config": {"name": "optimizer", "default": "Adam", "conditions": [], "values": ["Adam", "RMSprop", "Adadelta"], "ordered": false}}, {"class_name": "Int", "config": {"name": "units", "default": null, "conditions": [], "min_value": 16, "max_value": 256, "step": 16, "sampling": "linear"}}, {"class_name": "Int", "config": {"name": "hidden_layers", "default": null, "conditions": [], "min_value": 1, "max_value": 3, "step": 1, "sampling": "linear"}}, {"class_name": "Float", "config": {"name": "dropout", "default": 0.15, "conditions": [], "min_value": 0.15, "max_value": 0.45, "step": 0.15, "sampling": "linear"}}], "values": {"learning_rate": 0.005, "loss_fun": "MADL2", "optimizer": "Adam", "units": 16, "hidden_layers": 1, "dropout": 0.15}}, "start_order": ["00", "01", "02", "03", "04", "05", "06", "07", "08", "09", "10", "11", "12", "13", "14"], "end_order": ["00", "01", "02", "03", "04", "05", "06", "07", "08", "09", "10", "11", "12", "13", "14"], "run_times": {"00": 1, "01": 1, "02": 1, "03": 1, "04": 1, "05": 1, "06": 1, "07": 1, "08": 1, "09": 1, "10": 1, "11": 1, "12": 1, "13": 1, "14": 1}, "retry_queue": [], "seed": 4226, "seed_state": 4316, "tried_so_far": ["791d945eafc7630166e525d5e5ca2fa0", "6c19adfaf9f9edf86ab8e2358c18e996", "f9b86db37e417f7fd16aa24e9eed9a38", "09b0badbc8ca99a55b35cd604ef8e13a", "b3095fe5c3b3650f60b999d0f0cdb719", "b9e8f509576d3bd0269140fe89ec73dc", "ee96ba8955a10902cc74ceaf769ddb8e", "a23efecc3b0ef4087308aacec9c92767", "ee61fc05a9742399a8c5a310c9ed7760", "3fa5c76c820198f468eb6a40bbc7c49a", "62b6f08d1119e1137baf863b2f1a3543", "3960550d400187eebd787afb0ca6ea88", "751b73d705d7ebe7f5ae67fb0e51cfa9", "ce176272cd8f316f4aa6765dd0f1ada5", "45a37934681a8310fc89612b7a9dad21"], "id_to_hash": {"00": "b9e8f509576d3bd0269140fe89ec73dc", "01": "6c19adfaf9f9edf86ab8e2358c18e996", "02": "b3095fe5c3b3650f60b999d0f0cdb719", "03": "ce176272cd8f316f4aa6765dd0f1ada5", "04": "751b73d705d7ebe7f5ae67fb0e51cfa9", "05": "791d945eafc7630166e525d5e5ca2fa0", "06": "62b6f08d1119e1137baf863b2f1a3543", "07": "a23efecc3b0ef4087308aacec9c92767", "08": "f9b86db37e417f7fd16aa24e9eed9a38", "09": "ee96ba8955a10902cc74ceaf769ddb8e", "10": "3960550d400187eebd787afb0ca6ea88", "11": "45a37934681a8310fc89612b7a9dad21", "12": "09b0badbc8ca99a55b35cd604ef8e13a", "13": "ee61fc05a9742399a8c5a310c9ed7760", "14": "3fa5c76c820198f468eb6a40bbc7c49a"}, "display": {"search_start": "2023-10-29T05:03:18.517876", "trial_start": {"00": "2023-10-29T05:03:18.517876", "01": "2023-10-29T05:03:31.570846", "02": "2023-10-29T05:03:42.673741", "03": "2023-10-29T05:04:07.420311", "04": "2023-10-29T05:04:25.930310", "05": "2023-10-29T05:04:37.251389", "06": "2023-10-29T05:04:50.596178", "07": "2023-10-29T05:05:12.540225", "08": "2023-10-29T05:05:20.010178", "09": "2023-10-29T05:05:40.314573", "10": "2023-10-29T05:06:13.183124", "11": "2023-10-29T05:06:28.188357", "12": "2023-10-29T05:06:44.245923", "13": "2023-10-29T05:07:01.346311", "14": "2023-10-29T05:07:14.679318"}, "trial_number": {"00": 1, "01": 2, "02": 3, "03": 4, "04": 5, "05": 6, "06": 7, "07": 8, "08": 9, "09": 10, "10": 11, "11": 12, "12": 13, "13": 14, "14": 15}}, "num_initial_points": null, "alpha": 0.0001, "beta": 2.6}